odoo8_addon_document_page_procedure-8.0.1.0.0.99.dev5-py2.7-nspkg.pth
odoo8_addon_document_page_procedure-8.0.1.0.0.99.dev5.dist-info/DESCRIPTION.rst
odoo8_addon_document_page_procedure-8.0.1.0.0.99.dev5.dist-info/METADATA
odoo8_addon_document_page_procedure-8.0.1.0.0.99.dev5.dist-info/RECORD
odoo8_addon_document_page_procedure-8.0.1.0.0.99.dev5.dist-info/WHEEL
odoo8_addon_document_page_procedure-8.0.1.0.0.99.dev5.dist-info/metadata.json
odoo8_addon_document_page_procedure-8.0.1.0.0.99.dev5.dist-info/namespace_packages.txt
odoo8_addon_document_page_procedure-8.0.1.0.0.99.dev5.dist-info/top_level.txt
odoo_addons/document_page_procedure/__init__.py
odoo_addons/document_page_procedure/__openerp__.py
odoo_addons/document_page_procedure/data/document_page.xml
odoo_addons/document_page_procedure/demo/document_page.xml
odoo_addons/document_page_procedure/i18n/de.po
odoo_addons/document_page_procedure/i18n/document_page_procedure.pot
odoo_addons/document_page_procedure/i18n/es.po
odoo_addons/document_page_procedure/i18n/fr.po
odoo_addons/document_page_procedure/i18n/hu.po
odoo_addons/document_page_procedure/i18n/id.po
odoo_addons/document_page_procedure/i18n/nb.po
odoo_addons/document_page_procedure/i18n/pt_BR.po
odoo_addons/document_page_procedure/i18n/sl.po
odoo_addons/document_page_procedure/i18n/sv.po
odoo_addons/document_page_procedure/i18n/vi.po
odoo_addons/document_page_procedure/migrations/7.0.1.0/pre-migration.py
odoo_addons/document_page_procedure/static/description/icon.png
odoo_addons/document_page_procedure/views/document_page.xml
